ultru_client/__init__.py
ultru_client/cli.py
ultru_client/shell.py
ultru_client/utils/__init__.py
ultru_client/utils/auth.py
ultru_client/utils/base.py
ultru_client/utils/config.py
ultru_client/utils/engagements.py
ultru_client/utils/exceptions.py
ultru_client/utils/filters.py
ultru_client/utils/globals.py
ultru_client/utils/jobs.py
ultru_client/utils/query.py
ultru_client/utils/record_types.py
ultru_client/utils/scores.py
ultru_client/utils/sort.py
ultru_client/utils/utils.py
ultru_client/utils/contrib/__init__.py
ultru_client/utils/contrib/cognito_util/__init__.py
ultru_client/utils/contrib/cognito_util/aws_srp.py
ultru_client-1.2.2.dist-info/LICENSE
ultru_client-1.2.2.dist-info/METADATA
ultru_client-1.2.2.dist-info/WHEEL
ultru_client-1.2.2.dist-info/entry_points.txt
ultru_client-1.2.2.dist-info/top_level.txt
ultru_client-1.2.2.dist-info/RECORD
